odoo10_addon_l10n_it_fatturapa_out_triple_discount-10.0.2.0.0-nspkg.pth
odoo/addons/l10n_it_fatturapa_out_triple_discount/README.rst
odoo/addons/l10n_it_fatturapa_out_triple_discount/__init__.py
odoo/addons/l10n_it_fatturapa_out_triple_discount/__manifest__.py
odoo/addons/l10n_it_fatturapa_out_triple_discount/i18n/l10n_it_fatturapa_out_triple_discount.pot
odoo/addons/l10n_it_fatturapa_out_triple_discount/readme/CONTRIBUTORS.rst
odoo/addons/l10n_it_fatturapa_out_triple_discount/readme/DESCRIPTION.rst
odoo/addons/l10n_it_fatturapa_out_triple_discount/static/description/icon.png
odoo/addons/l10n_it_fatturapa_out_triple_discount/static/description/index.html
odoo/addons/l10n_it_fatturapa_out_triple_discount/tests/__init__.py
odoo/addons/l10n_it_fatturapa_out_triple_discount/tests/test_fatturapa_triple_discount.py
odoo/addons/l10n_it_fatturapa_out_triple_discount/tests/data/IT06363391001_00001.xml
odoo/addons/l10n_it_fatturapa_out_triple_discount/wizard/__init__.py
odoo/addons/l10n_it_fatturapa_out_triple_discount/wizard/wizard_export_fatturapa.py
odoo10_addon_l10n_it_fatturapa_out_triple_discount-10.0.2.0.0.dist-info/METADATA
odoo10_addon_l10n_it_fatturapa_out_triple_discount-10.0.2.0.0.dist-info/WHEEL
odoo10_addon_l10n_it_fatturapa_out_triple_discount-10.0.2.0.0.dist-info/namespace_packages.txt
odoo10_addon_l10n_it_fatturapa_out_triple_discount-10.0.2.0.0.dist-info/top_level.txt
odoo10_addon_l10n_it_fatturapa_out_triple_discount-10.0.2.0.0.dist-info/RECORD
